oberoon/__init__.py
oberoon/app.py
oberoon/middleware.py
oberoon/response.py
oberoon-0.1.3.dist-info/METADATA
oberoon-0.1.3.dist-info/WHEEL
oberoon-0.1.3.dist-info/top_level.txt
oberoon-0.1.3.dist-info/RECORD
